[
  {
    "domain": "ospcyberacademy.com",
    "page": "about.html",
    "section": "General",
    "text": "About - OSP Cyber Academy",
    "source_path": "D:\\ZORO\\company_intel\\data\\ospcyberacademy.com\\about.html",
    "page_title": "About - OSP Cyber Academy",
    "meta_description": "About Us OSP Cyber Academy are a managed service provider […]"
  },
  {
    "domain": "ospcyberacademy.com",
    "page": "about/index.html",
    "section": "General",
    "text": "About - OSP Cyber Academy",
    "source_path": "D:\\ZORO\\company_intel\\data\\ospcyberacademy.com\\about\\index.html",
    "page_title": "About - OSP Cyber Academy",
    "meta_description": "About Us OSP Cyber Academy are a managed service provider […]"
  },
  {
    "domain": "ospcyberacademy.com",
    "page": "acceptable-use-policy/index.html",
    "section": "General",
    "text": "Acceptable Use Policy - OSP Cyber Academy",
    "source_path": "D:\\ZORO\\company_intel\\data\\ospcyberacademy.com\\acceptable-use-policy\\index.html",
    "page_title": "Acceptable Use Policy - OSP Cyber Academy",
    "meta_description": "This is the acceptable use policy, which, together with our […]"
  },
  {
    "domain": "ospcyberacademy.com",
    "page": "blog/index.html",
    "section": "General",
    "text": "Blog - OSP Cyber Academy",
    "source_path": "D:\\ZORO\\company_intel\\data\\ospcyberacademy.com\\blog\\index.html",
    "page_title": "Blog - OSP Cyber Academy",
    "meta_description": ""
  },
  {
    "domain": "ospcyberacademy.com",
    "page": "blog/page/2/index.html",
    "section": "General",
    "text": "Blog - Page 2 of 3 - OSP Cyber Academy",
    "source_path": "D:\\ZORO\\company_intel\\data\\ospcyberacademy.com\\blog\\page\\2\\index.html",
    "page_title": "Blog - Page 2 of 3 - OSP Cyber Academy",
    "meta_description": ""
  },
  {
    "domain": "ospcyberacademy.com",
    "page": "blog/page/3/index.html",
    "section": "General",
    "text": "Blog - Page 3 of 3 - OSP Cyber Academy",
    "source_path": "D:\\ZORO\\company_intel\\data\\ospcyberacademy.com\\blog\\page\\3\\index.html",
    "page_title": "Blog - Page 3 of 3 - OSP Cyber Academy",
    "meta_description": ""
  },
  {
    "domain": "ospcyberacademy.com",
    "page": "business-privacy-notice/index.html",
    "section": "General",
    "text": "Business Privacy Notice - OSP Cyber Academy",
    "source_path": "D:\\ZORO\\company_intel\\data\\ospcyberacademy.com\\business-privacy-notice\\index.html",
    "page_title": "Business Privacy Notice - OSP Cyber Academy",
    "meta_description": "BUSINESS CONTACT/ASSOCIATE/CONSULTANT PRIVACY NOTICE BUSINESS CONTACT/ASSOCIATE/CONSULTANT PRIVACY NOTICE Title Business […]"
  },
  {
    "domain": "ospcyberacademy.com",
    "page": "cart/index.html",
    "section": "General",
    "text": "Cart - OSP Cyber Academy",
    "source_path": "D:\\ZORO\\company_intel\\data\\ospcyberacademy.com\\cart\\index.html",
    "page_title": "Cart - OSP Cyber Academy",
    "meta_description": ""
  },
  {
    "domain": "ospcyberacademy.com",
    "page": "ccoe-provides-ncsc-assured-training/index.html",
    "section": "General",
    "text": "CCoE Provides NCSC-Assured Training - OSP Cyber Academy",
    "source_path": "D:\\ZORO\\company_intel\\data\\ospcyberacademy.com\\ccoe-provides-ncsc-assured-training\\index.html",
    "page_title": "CCoE Provides NCSC-Assured Training - OSP Cyber Academy",
    "meta_description": "iESE has teamed up with UK Government-certified cyber security and […]"
  },
  {
    "domain": "ospcyberacademy.com",
    "page": "ccoe-webinar-educating-your-way-to-cyber-success/index.html",
    "section": "General",
    "text": "CCoE Webinar - Educating Your Way to Cyber Success - OSP Cyber Academy",
    "source_path": "D:\\ZORO\\company_intel\\data\\ospcyberacademy.com\\ccoe-webinar-educating-your-way-to-cyber-success\\index.html",
    "page_title": "CCoE Webinar - Educating Your Way to Cyber Success - OSP Cyber Academy",
    "meta_description": "Our COO, Irene Coyle participated in the webinar, 'Educating your way to cyber success.'"
  },
  {
    "domain": "ospcyberacademy.com",
    "page": "celerity-presents-security-awareness-training/index.html",
    "section": "General",
    "text": "Celerity Presents: Security Awareness Training - OSP Cyber Academy",
    "source_path": "D:\\ZORO\\company_intel\\data\\ospcyberacademy.com\\celerity-presents-security-awareness-training\\index.html",
    "page_title": "Celerity Presents: Security Awareness Training - OSP Cyber Academy",
    "meta_description": "Featuring: Richard Preece, Chief Training Officer at OSP Cyber Academy Celerity […]"
  },
  {
    "domain": "ospcyberacademy.com",
    "page": "contact.html",
    "section": "General",
    "text": "Contact - OSP Cyber Academy",
    "source_path": "D:\\ZORO\\company_intel\\data\\ospcyberacademy.com\\contact.html",
    "page_title": "Contact - OSP Cyber Academy",
    "meta_description": "Contact OSP Thank you for your interest. If you have […]"
  },
  {
    "domain": "ospcyberacademy.com",
    "page": "contact/index.html",
    "section": "General",
    "text": "Contact - OSP Cyber Academy",
    "source_path": "D:\\ZORO\\company_intel\\data\\ospcyberacademy.com\\contact\\index.html",
    "page_title": "Contact - OSP Cyber Academy",
    "meta_description": "Contact OSP Thank you for your interest. If you have […]"
  },
  {
    "domain": "ospcyberacademy.com",
    "page": "cookie-policy.html",
    "section": "General",
    "text": "Cookie Policy - OSP Cyber Academy",
    "source_path": "D:\\ZORO\\company_intel\\data\\ospcyberacademy.com\\cookie-policy.html",
    "page_title": "Cookie Policy - OSP Cyber Academy",
    "meta_description": "About this cookie policy. This Cookie Policy explains what cookies […]"
  },
  {
    "domain": "ospcyberacademy.com",
    "page": "cookie-policy/index.html",
    "section": "General",
    "text": "Cookie Policy - OSP Cyber Academy",
    "source_path": "D:\\ZORO\\company_intel\\data\\ospcyberacademy.com\\cookie-policy\\index.html",
    "page_title": "Cookie Policy - OSP Cyber Academy",
    "meta_description": "About this cookie policy. This Cookie Policy explains what cookies […]"
  },
  {
    "domain": "ospcyberacademy.com",
    "page": "cyberprism-develops-an-online-ot-security-course-with-osp-cyber-academy/index.html",
    "section": "General",
    "text": "CyberPrism develops an online OT security course with OSP Cyber Academy - OSP Cyber Academy",
    "source_path": "D:\\ZORO\\company_intel\\data\\ospcyberacademy.com\\cyberprism-develops-an-online-ot-security-course-with-osp-cyber-academy\\index.html",
    "page_title": "CyberPrism develops an online OT security course with OSP Cyber Academy - OSP Cyber Academy",
    "meta_description": "Produced as a partnership between OSP Cyber Academy and industrial […]"
  },
  {
    "domain": "ospcyberacademy.com",
    "page": "elearning.html",
    "section": "General",
    "text": "eLearning Courses - OSP Cyber Academy",
    "source_path": "D:\\ZORO\\company_intel\\data\\ospcyberacademy.com\\elearning.html",
    "page_title": "eLearning Courses - OSP Cyber Academy",
    "meta_description": "eLearning Courses Our courses are developed by experienced Data Protection […]"
  },
  {
    "domain": "ospcyberacademy.com",
    "page": "elearning/index.html",
    "section": "General",
    "text": "eLearning Courses - OSP Cyber Academy",
    "source_path": "D:\\ZORO\\company_intel\\data\\ospcyberacademy.com\\elearning\\index.html",
    "page_title": "eLearning Courses - OSP Cyber Academy",
    "meta_description": "eLearning Courses Our courses are developed by experienced Data Protection […]"
  },
  {
    "domain": "ospcyberacademy.com",
    "page": "elevate-your-data-protection-game-why-data-protection-training-matters/index.html",
    "section": "General",
    "text": "Elevate Your Data Protection Game: Why Data Protection Training Matters - OSP Cyber Academy",
    "source_path": "D:\\ZORO\\company_intel\\data\\ospcyberacademy.com\\elevate-your-data-protection-game-why-data-protection-training-matters\\index.html",
    "page_title": "Elevate Your Data Protection Game: Why Data Protection Training Matters - OSP Cyber Academy",
    "meta_description": "Elevate Your Data Protection Game: Why Data Protection Training Matters […]"
  },
  {
    "domain": "ospcyberacademy.com",
    "page": "escape-room-training/index.html",
    "section": "General",
    "text": "Escape Room Training - OSP Cyber Academy",
    "source_path": "D:\\ZORO\\company_intel\\data\\ospcyberacademy.com\\escape-room-training\\index.html",
    "page_title": "Escape Room Training - OSP Cyber Academy",
    "meta_description": "Escape Room Training Learn the Secrets of the Hackers and […]"
  },
  {
    "domain": "ospcyberacademy.com",
    "page": "icrs-2025-day-1/index.html",
    "section": "General",
    "text": "ICRS 2025 Day 1 - OSP Cyber Academy",
    "source_path": "D:\\ZORO\\company_intel\\data\\ospcyberacademy.com\\icrs-2025-day-1\\index.html",
    "page_title": "ICRS 2025 Day 1 - OSP Cyber Academy",
    "meta_description": "PURCHASE TICKETS VIEW AGENDA VIEW DAY 2 EVENT PARTNERS DIAMOND […]"
  },
  {
    "domain": "ospcyberacademy.com",
    "page": "icrs-2025-day-2/index.html",
    "section": "General",
    "text": "ICRS 2025 Day 2 - OSP Cyber Academy",
    "source_path": "D:\\ZORO\\company_intel\\data\\ospcyberacademy.com\\icrs-2025-day-2\\index.html",
    "page_title": "ICRS 2025 Day 2 - OSP Cyber Academy",
    "meta_description": "PURCHASE TICKETS VIEW AGENDA VIEW DAY 1 EVENT PARTNERS DIAMOND […]"
  },
  {
    "domain": "ospcyberacademy.com",
    "page": "icrs-2025/index.html",
    "section": "Contact Information",
    "text": "Phone numbers: 0012345678910, 00123456789, 200.001234567891\nEmail*\nPhone",
    "source_path": "D:\\ZORO\\company_intel\\data\\ospcyberacademy.com\\icrs-2025\\index.html",
    "page_title": "International Cyber Risk Symposium 2025 - OSP Cyber Academy",
    "meta_description": "Get ready for two days of Keynotes Workshops Deep Dives […]",
    "structured_data": {
      "emails": [],
      "phones": [
        "0012345678910",
        "00123456789",
        "200.001234567891"
      ],
      "social_links": {
        "facebook": "https://www.facebook.com/OSPCyberAcademy/",
        "linkedin": "https://www.linkedin.com/company/operationalsecurityprofessionalsgrouplimited/",
        "x": "https://twitter.com/OSPcyberacademy",
        "youtube": "https://www.youtube.com/channel/UCsWyl7VLp7tdw5X32aUOsLw"
      }
    }
  },
  {
    "domain": "ospcyberacademy.com",
    "page": "icrs-2025/index.html",
    "section": "General",
    "text": "International Cyber Risk Symposium 2025 - OSP Cyber Academy",
    "source_path": "D:\\ZORO\\company_intel\\data\\ospcyberacademy.com\\icrs-2025\\index.html",
    "page_title": "International Cyber Risk Symposium 2025 - OSP Cyber Academy",
    "meta_description": "Get ready for two days of Keynotes Workshops Deep Dives […]"
  },
  {
    "domain": "ospcyberacademy.com",
    "page": "index.html",
    "section": "General",
    "text": "OSP Cyber Academy - NCSC Assured Cyber Awareness Training",
    "source_path": "D:\\ZORO\\company_intel\\data\\ospcyberacademy.com\\index.html",
    "page_title": "OSP Cyber Academy - NCSC Assured Cyber Awareness Training",
    "meta_description": "OSP provide NCSC assured Cyber Security training - Enabling organisations to reduce risk, improve cyber resilience and demonstrate compliance"
  },
  {
    "domain": "ospcyberacademy.com",
    "page": "integrating-ai-into-the-workplace/index.html",
    "section": "General",
    "text": "Integrating AI into the Workplace - OSP Cyber Academy",
    "source_path": "D:\\ZORO\\company_intel\\data\\ospcyberacademy.com\\integrating-ai-into-the-workplace\\index.html",
    "page_title": "Integrating AI into the Workplace - OSP Cyber Academy",
    "meta_description": "Artificial Intelligence (AI) is revolutionising the workplace, bringing both opportunities […]"
  },
  {
    "domain": "ospcyberacademy.com",
    "page": "knock-your-cyber-training-out-of-the-park/index.html",
    "section": "General",
    "text": "Knock your Cyber Training out of the Park: Let's Talk Cyber with Irene Coyle - OSP Cyber Academy",
    "source_path": "D:\\ZORO\\company_intel\\data\\ospcyberacademy.com\\knock-your-cyber-training-out-of-the-park\\index.html",
    "page_title": "Knock your Cyber Training out of the Park: Let's Talk Cyber with Irene Coyle - OSP Cyber Academy",
    "meta_description": "Let's Talk Cyber with our Chief Operating Officer Irene Coyle."
  },
  {
    "domain": "ospcyberacademy.com",
    "page": "lms-courses/index.html",
    "section": "General",
    "text": "LMS Courses - OSP Cyber Academy",
    "source_path": "D:\\ZORO\\company_intel\\data\\ospcyberacademy.com\\lms-courses\\index.html",
    "page_title": "LMS Courses - OSP Cyber Academy",
    "meta_description": "LMS Courses Our courses are developed by experienced Data Protection […]"
  },
  {
    "domain": "ospcyberacademy.com",
    "page": "may-2024-newsletter/index.html",
    "section": "General",
    "text": "May 2024 Newsletter - OSP Cyber Academy",
    "source_path": "D:\\ZORO\\company_intel\\data\\ospcyberacademy.com\\may-2024-newsletter\\index.html",
    "page_title": "May 2024 Newsletter - OSP Cyber Academy",
    "meta_description": "Welcome to our May newsletter!"
  },
  {
    "domain": "ospcyberacademy.com",
    "page": "my-account.html",
    "section": "General",
    "text": "My account - OSP Cyber Academy",
    "source_path": "D:\\ZORO\\company_intel\\data\\ospcyberacademy.com\\my-account.html",
    "page_title": "My account - OSP Cyber Academy",
    "meta_description": "My Account Welcome to your account page. My Courses My […]"
  },
  {
    "domain": "ospcyberacademy.com",
    "page": "my-account/index.html",
    "section": "General",
    "text": "My account - OSP Cyber Academy",
    "source_path": "D:\\ZORO\\company_intel\\data\\ospcyberacademy.com\\my-account\\index.html",
    "page_title": "My account - OSP Cyber Academy",
    "meta_description": "My Account Welcome to your account page. My Courses My […]"
  },
  {
    "domain": "ospcyberacademy.com",
    "page": "my-account/lost-password/index.html",
    "section": "General",
    "text": "My account - OSP Cyber Academy",
    "source_path": "D:\\ZORO\\company_intel\\data\\ospcyberacademy.com\\my-account\\lost-password\\index.html",
    "page_title": "My account - OSP Cyber Academy",
    "meta_description": "My Account Welcome to your account page. My Courses My […]"
  },
  {
    "domain": "ospcyberacademy.com",
    "page": "osp-join-forces-with-wood-rgu-to-change-cyber-behaviour/index.html",
    "section": "General",
    "text": "OSP Join Forces with Wood & RGU to Change Cyber Behaviour - OSP Cyber Academy",
    "source_path": "D:\\ZORO\\company_intel\\data\\ospcyberacademy.com\\osp-join-forces-with-wood-rgu-to-change-cyber-behaviour\\index.html",
    "page_title": "OSP Join Forces with Wood & RGU to Change Cyber Behaviour - OSP Cyber Academy",
    "meta_description": "OSP Cyber Academy, Wood, and Robert Gordon University (RGU) have […]"
  },
  {
    "domain": "ospcyberacademy.com",
    "page": "partners/index.html",
    "section": "General",
    "text": "Partners - OSP Cyber Academy",
    "source_path": "D:\\ZORO\\company_intel\\data\\ospcyberacademy.com\\partners\\index.html",
    "page_title": "Partners - OSP Cyber Academy",
    "meta_description": "Become an OSP Affiliate Partner Join our Affiliate Partner Programme […]"
  },
  {
    "domain": "ospcyberacademy.com",
    "page": "privacy-policy.html",
    "section": "General",
    "text": "Privacy Policy - OSP Cyber Academy",
    "source_path": "D:\\ZORO\\company_intel\\data\\ospcyberacademy.com\\privacy-policy.html",
    "page_title": "Privacy Policy - OSP Cyber Academy",
    "meta_description": "Website Privacy Notice 1. INTRODUCTION This privacy notice provides you […]"
  },
  {
    "domain": "ospcyberacademy.com",
    "page": "privacy-policy/index.html",
    "section": "General",
    "text": "Privacy Policy - OSP Cyber Academy",
    "source_path": "D:\\ZORO\\company_intel\\data\\ospcyberacademy.com\\privacy-policy\\index.html",
    "page_title": "Privacy Policy - OSP Cyber Academy",
    "meta_description": "Website Privacy Notice 1. INTRODUCTION This privacy notice provides you […]"
  },
  {
    "domain": "ospcyberacademy.com",
    "page": "product/agent-cyber-awareness-course/index.html",
    "section": "General",
    "text": "Agent Cyber Awareness Course - OSP Cyber Academy",
    "source_path": "D:\\ZORO\\company_intel\\data\\ospcyberacademy.com\\product\\agent-cyber-awareness-course\\index.html",
    "page_title": "Agent Cyber Awareness Course - OSP Cyber Academy",
    "meta_description": "£15 per user/seat This is an annual subscription product, managed via your account. Please see our T&Cs for more details."
  },
  {
    "domain": "ospcyberacademy.com",
    "page": "product/cyber-investigator-foundation/index.html",
    "section": "General",
    "text": "Cyber Investigator Foundation - OSP Cyber Academy",
    "source_path": "D:\\ZORO\\company_intel\\data\\ospcyberacademy.com\\product\\cyber-investigator-foundation\\index.html",
    "page_title": "Cyber Investigator Foundation - OSP Cyber Academy",
    "meta_description": "Course Code: INVEST1 Course Duration: 3 days Level 2: Foundation Next virtual course: enquire for availability Next classroom course: enquire for availability"
  },
  {
    "domain": "ospcyberacademy.com",
    "page": "product/cyber-risk-and-resilience-managers-awareness-course/index.html",
    "section": "General",
    "text": "Half Day Cyber Risk & Resilience Board & Executive Awareness Course - OSP Cyber Academy",
    "source_path": "D:\\ZORO\\company_intel\\data\\ospcyberacademy.com\\product\\cyber-risk-and-resilience-managers-awareness-course\\index.html",
    "page_title": "Half Day Cyber Risk & Resilience Board & Executive Awareness Course - OSP Cyber Academy",
    "meta_description": "Course Duration: Half day Next virtual course: enquire for availability Next classroom course: enquire for availability"
  },
  {
    "domain": "ospcyberacademy.com",
    "page": "product/cyber-risk-management-course/index.html",
    "section": "General",
    "text": "Cyber Risk Management Course - OSP Cyber Academy",
    "source_path": "D:\\ZORO\\company_intel\\data\\ospcyberacademy.com\\product\\cyber-risk-management-course\\index.html",
    "page_title": "Cyber Risk Management Course - OSP Cyber Academy",
    "meta_description": "£125 per user/seat This course is an annual subscription product, you can manage your subscription in your account. Please see our T&Cs for more details. The aim of this introductory level course is to provide Senior Managers and Leaders with a better understanding and overview of cyber risk management."
  },
  {
    "domain": "ospcyberacademy.com",
    "page": "product/cyber-risk-resilience-board-executive-awareness-course/index.html",
    "section": "General",
    "text": "Full Day Cyber Risk & Resilience Board & Executive Awareness Course - OSP Cyber Academy",
    "source_path": "D:\\ZORO\\company_intel\\data\\ospcyberacademy.com\\product\\cyber-risk-resilience-board-executive-awareness-course\\index.html",
    "page_title": "Full Day Cyber Risk & Resilience Board & Executive Awareness Course - OSP Cyber Academy",
    "meta_description": "Course Duration: 1 day Next virtual course: enquire for availability Next classroom course: enquire for availability"
  },
  {
    "domain": "ospcyberacademy.com",
    "page": "product/cyber-secure-at-home-course/index.html",
    "section": "General",
    "text": "Cyber Secure At Home Course - OSP Cyber Academy",
    "source_path": "D:\\ZORO\\company_intel\\data\\ospcyberacademy.com\\product\\cyber-secure-at-home-course\\index.html",
    "page_title": "Cyber Secure At Home Course - OSP Cyber Academy",
    "meta_description": "£8 per user/seat This is an annual subscription product, managed via your account. Please see our T&Cs for more details. This course can be taken as part of an information Security or Cyber Resilience training programme or as a standalone course to raise awareness amongst your staff for working from home securely."
  },
  {
    "domain": "ospcyberacademy.com",
    "page": "product/cyber-secure-at-home-lms-package/index.html",
    "section": "Contact Information",
    "text": "Phone numbers: 1-500501-1000, 1001-25002501-5000, 5001-1500015001",
    "source_path": "D:\\ZORO\\company_intel\\data\\ospcyberacademy.com\\product\\cyber-secure-at-home-lms-package\\index.html",
    "page_title": "Cyber Secure At Home LMS Package - OSP Cyber Academy",
    "meta_description": "The pricing model is based on the size of the organisation. This is a one-year renewable licence product. Please see our T&Cs for more details.",
    "structured_data": {
      "emails": [],
      "phones": [
        "1-500501-1000",
        "1001-25002501-5000",
        "5001-1500015001"
      ],
      "social_links": {
        "facebook": "https://www.facebook.com/OSPCyberAcademy/",
        "linkedin": "https://www.linkedin.com/company/operationalsecurityprofessionalsgrouplimited/",
        "x": "https://twitter.com/OSPcyberacademy",
        "youtube": "https://www.youtube.com/channel/UCsWyl7VLp7tdw5X32aUOsLw"
      }
    }
  },
  {
    "domain": "ospcyberacademy.com",
    "page": "product/cyber-secure-at-home-lms-package/index.html",
    "section": "General",
    "text": "Cyber Secure At Home LMS Package - OSP Cyber Academy",
    "source_path": "D:\\ZORO\\company_intel\\data\\ospcyberacademy.com\\product\\cyber-secure-at-home-lms-package\\index.html",
    "page_title": "Cyber Secure At Home LMS Package - OSP Cyber Academy",
    "meta_description": "The pricing model is based on the size of the organisation. This is a one-year renewable licence product. Please see our T&Cs for more details."
  },
  {
    "domain": "ospcyberacademy.com",
    "page": "product/cyber-security-staff-awareness-course-lms-package/index.html",
    "section": "Contact Information",
    "text": "Phone numbers: 1-500501-1000, 1001-25002501-5000, 5001-1500015001",
    "source_path": "D:\\ZORO\\company_intel\\data\\ospcyberacademy.com\\product\\cyber-security-staff-awareness-course-lms-package\\index.html",
    "page_title": "Cyber Security Staff Awareness LMS Package - OSP Cyber Academy",
    "meta_description": "The pricing model is based on the size of the organisation. This Course is assured in association with the National Cyber Security Centre. This is a one-year renewable licence product. Please see our T&Cs for more details.",
    "structured_data": {
      "emails": [],
      "phones": [
        "1-500501-1000",
        "1001-25002501-5000",
        "5001-1500015001"
      ],
      "social_links": {
        "facebook": "https://www.facebook.com/OSPCyberAcademy/",
        "linkedin": "https://www.linkedin.com/company/operationalsecurityprofessionalsgrouplimited/",
        "x": "https://twitter.com/OSPcyberacademy",
        "youtube": "https://www.youtube.com/channel/UCsWyl7VLp7tdw5X32aUOsLw"
      }
    }
  },
  {
    "domain": "ospcyberacademy.com",
    "page": "product/cyber-security-staff-awareness-course-lms-package/index.html",
    "section": "General",
    "text": "Cyber Security Staff Awareness LMS Package - OSP Cyber Academy",
    "source_path": "D:\\ZORO\\company_intel\\data\\ospcyberacademy.com\\product\\cyber-security-staff-awareness-course-lms-package\\index.html",
    "page_title": "Cyber Security Staff Awareness LMS Package - OSP Cyber Academy",
    "meta_description": "The pricing model is based on the size of the organisation. This Course is assured in association with the National Cyber Security Centre. This is a one-year renewable licence product. Please see our T&Cs for more details."
  },
  {
    "domain": "ospcyberacademy.com",
    "page": "product/cyber-security-staff-awareness-course.html",
    "section": "General",
    "text": "Cyber Security Staff Awareness Course - OSP Cyber Academy",
    "source_path": "D:\\ZORO\\company_intel\\data\\ospcyberacademy.com\\product\\cyber-security-staff-awareness-course.html",
    "page_title": "Cyber Security Staff Awareness Course - OSP Cyber Academy",
    "meta_description": "£20 per user/seat This is an annual subscription product, managed via your account. Please see our T&Cs for more details. Enquire for pricing on orders of 500+ courses."
  },
  {
    "domain": "ospcyberacademy.com",
    "page": "product/cyber-security-staff-awareness-course/index.html",
    "section": "General",
    "text": "Cyber Security Staff Awareness Course - OSP Cyber Academy",
    "source_path": "D:\\ZORO\\company_intel\\data\\ospcyberacademy.com\\product\\cyber-security-staff-awareness-course\\index.html",
    "page_title": "Cyber Security Staff Awareness Course - OSP Cyber Academy",
    "meta_description": "£20 per user/seat This is an annual subscription product, managed via your account. Please see our T&Cs for more details. Enquire for pricing on orders of 500+ courses."
  },
  {
    "domain": "ospcyberacademy.com",
    "page": "product/data-breach-course/index.html",
    "section": "General",
    "text": "Data Breach Course - OSP Cyber Academy",
    "source_path": "D:\\ZORO\\company_intel\\data\\ospcyberacademy.com\\product\\data-breach-course\\index.html",
    "page_title": "Data Breach Course - OSP Cyber Academy",
    "meta_description": "£12 per user/seat This is an annual subscription product, managed via your account. Please see our T&Cs for more details. This course can be taken as part of an information Security or Cyber Resilience training programme or as a standalone course to raise awareness amongst your staff for data breaches."
  },
  {
    "domain": "ospcyberacademy.com",
    "page": "product/data-breach-lms-package/index.html",
    "section": "Contact Information",
    "text": "Phone numbers: 1-500501-1000, 1001-25002501-5000, 5001-1500015001",
    "source_path": "D:\\ZORO\\company_intel\\data\\ospcyberacademy.com\\product\\data-breach-lms-package\\index.html",
    "page_title": "Data Breach LMS Package - OSP Cyber Academy",
    "meta_description": "The pricing model is based on the size of the organisation. This is a one-year renewable licence product. Please see our T&Cs for more details.",
    "structured_data": {
      "emails": [],
      "phones": [
        "1-500501-1000",
        "1001-25002501-5000",
        "5001-1500015001"
      ],
      "social_links": {
        "facebook": "https://www.facebook.com/OSPCyberAcademy/",
        "linkedin": "https://www.linkedin.com/company/operationalsecurityprofessionalsgrouplimited/",
        "x": "https://twitter.com/OSPcyberacademy",
        "youtube": "https://www.youtube.com/channel/UCsWyl7VLp7tdw5X32aUOsLw"
      }
    }
  },
  {
    "domain": "ospcyberacademy.com",
    "page": "product/data-breach-lms-package/index.html",
    "section": "General",
    "text": "Data Breach LMS Package - OSP Cyber Academy",
    "source_path": "D:\\ZORO\\company_intel\\data\\ospcyberacademy.com\\product\\data-breach-lms-package\\index.html",
    "page_title": "Data Breach LMS Package - OSP Cyber Academy",
    "meta_description": "The pricing model is based on the size of the organisation. This is a one-year renewable licence product. Please see our T&Cs for more details."
  },
  {
    "domain": "ospcyberacademy.com",
    "page": "product/data-protection-gdpr-one-day-awareness-course/index.html",
    "section": "General",
    "text": "Data Protection & GDPR Awareness Course - OSP Cyber Academy",
    "source_path": "D:\\ZORO\\company_intel\\data\\ospcyberacademy.com\\product\\data-protection-gdpr-one-day-awareness-course\\index.html",
    "page_title": "Data Protection & GDPR Awareness Course - OSP Cyber Academy",
    "meta_description": "Course Duration: 1 day Next virtual course: enquire for availability Next classroom course: enquire for availability"
  },
  {
    "domain": "ospcyberacademy.com",
    "page": "product/data-protection-gdpr-practitioner-course/index.html",
    "section": "General",
    "text": "Data Protection & GDPR Practitioner Course - OSP Cyber Academy",
    "source_path": "D:\\ZORO\\company_intel\\data\\ospcyberacademy.com\\product\\data-protection-gdpr-practitioner-course\\index.html",
    "page_title": "Data Protection & GDPR Practitioner Course - OSP Cyber Academy",
    "meta_description": "Course Duration: 3 1/2 days Next virtual course: enquire for availability Next classroom course: enquire for availability"
  },
  {
    "domain": "ospcyberacademy.com",
    "page": "product/digital-footprint-course/index.html",
    "section": "General",
    "text": "Digital Footprint Course - OSP Cyber Academy",
    "source_path": "D:\\ZORO\\company_intel\\data\\ospcyberacademy.com\\product\\digital-footprint-course\\index.html",
    "page_title": "Digital Footprint Course - OSP Cyber Academy",
    "meta_description": "£8 per user/seat This is an annual subscription product, managed via your account. Please see our T&Cs for more details. This course can be taken as part of an information Security or Cyber Resilience training programme or as a standalone course to raise awareness amongst your staff about their digital footprint."
  },
  {
    "domain": "ospcyberacademy.com",
    "page": "product/gdpr-staff-awareness-course-lms-package/index.html",
    "section": "Contact Information",
    "text": "Phone numbers: 1-500501-1000, 1001-25002501-5000, 5001-1500015001",
    "source_path": "D:\\ZORO\\company_intel\\data\\ospcyberacademy.com\\product\\gdpr-staff-awareness-course-lms-package\\index.html",
    "page_title": "GDPR Staff Awareness LMS Package - OSP Cyber Academy",
    "meta_description": "The pricing model is based on the size of the organisation. This Course is assured in association with the National Cyber Security Centre. This is a one-year renewable licence product. Please see our T&Cs for more details.",
    "structured_data": {
      "emails": [],
      "phones": [
        "1-500501-1000",
        "1001-25002501-5000",
        "5001-1500015001"
      ],
      "social_links": {
        "facebook": "https://www.facebook.com/OSPCyberAcademy/",
        "linkedin": "https://www.linkedin.com/company/operationalsecurityprofessionalsgrouplimited/",
        "x": "https://twitter.com/OSPcyberacademy",
        "youtube": "https://www.youtube.com/channel/UCsWyl7VLp7tdw5X32aUOsLw"
      }
    }
  },
  {
    "domain": "ospcyberacademy.com",
    "page": "product/gdpr-staff-awareness-course-lms-package/index.html",
    "section": "General",
    "text": "GDPR Staff Awareness LMS Package - OSP Cyber Academy",
    "source_path": "D:\\ZORO\\company_intel\\data\\ospcyberacademy.com\\product\\gdpr-staff-awareness-course-lms-package\\index.html",
    "page_title": "GDPR Staff Awareness LMS Package - OSP Cyber Academy",
    "meta_description": "The pricing model is based on the size of the organisation. This Course is assured in association with the National Cyber Security Centre. This is a one-year renewable licence product. Please see our T&Cs for more details."
  },
  {
    "domain": "ospcyberacademy.com",
    "page": "product/gdpr-staff-awareness-course.html",
    "section": "General",
    "text": "GDPR Staff Awareness Course - OSP Cyber Academy",
    "source_path": "D:\\ZORO\\company_intel\\data\\ospcyberacademy.com\\product\\gdpr-staff-awareness-course.html",
    "page_title": "GDPR Staff Awareness Course - OSP Cyber Academy",
    "meta_description": "£20 per user/seat This is an annual subscription product, managed via your account. Please see our T&Cs for more details. Enquire for pricing on orders of 500+ courses."
  },
  {
    "domain": "ospcyberacademy.com",
    "page": "product/gdpr-staff-awareness-course/index.html",
    "section": "General",
    "text": "GDPR Staff Awareness Course - OSP Cyber Academy",
    "source_path": "D:\\ZORO\\company_intel\\data\\ospcyberacademy.com\\product\\gdpr-staff-awareness-course\\index.html",
    "page_title": "GDPR Staff Awareness Course - OSP Cyber Academy",
    "meta_description": "£20 per user/seat This is an annual subscription product, managed via your account. Please see our T&Cs for more details. Enquire for pricing on orders of 500+ courses."
  },
  {
    "domain": "ospcyberacademy.com",
    "page": "product/ics-managers-security-fundamentals-course/index.html",
    "section": "General",
    "text": "ICS Managers Security Fundamentals Course - OSP Cyber Academy",
    "source_path": "D:\\ZORO\\company_intel\\data\\ospcyberacademy.com\\product\\ics-managers-security-fundamentals-course\\index.html",
    "page_title": "ICS Managers Security Fundamentals Course - OSP Cyber Academy",
    "meta_description": "The APMG International and swirl device logo is a trade mark of the APM Group Limited, used under permission of the APM Group Limited. All rights reserved. This course is assured in association with the National Cyber Security Centre Training Scheme. Course Code: ICS110 Course Duration: 1 day Level 1: Awareness Next virtual course: enquire for availability Next classroom course: enquire for availability"
  },
  {
    "domain": "ospcyberacademy.com",
    "page": "product/ics-practitioners-security/index.html",
    "section": "General",
    "text": "ICS Practitioners Security - OSP Cyber Academy",
    "source_path": "D:\\ZORO\\company_intel\\data\\ospcyberacademy.com\\product\\ics-practitioners-security\\index.html",
    "page_title": "ICS Practitioners Security - OSP Cyber Academy",
    "meta_description": "The APMG International and swirl device logo is a trade mark of the APM Group Limited, used under permission of the APM Group Limited. All rights reserved. This course is assured in association with the National Cyber Security Centre Training Scheme. Course Code: ICS203 Course Duration: 2 days Level 2: Foundation Next virtual course: enquire for availability Next classroom course: 15th to 16th October / 12th to 13th November"
  },
  {
    "domain": "ospcyberacademy.com",
    "page": "product/ics-security-incident-response-fundamentals/index.html",
    "section": "General",
    "text": "ICS Security Incident Response Fundamentals - OSP Cyber Academy",
    "source_path": "D:\\ZORO\\company_intel\\data\\ospcyberacademy.com\\product\\ics-security-incident-response-fundamentals\\index.html",
    "page_title": "ICS Security Incident Response Fundamentals - OSP Cyber Academy",
    "meta_description": "Course Code: ICS202 Course Duration: 2 days Level 2: Foundation Next virtual course: enquire for availability Next classroom course: enquire for availability"
  },
  {
    "domain": "ospcyberacademy.com",
    "page": "product/ics4ics-workshop/index.html",
    "section": "General",
    "text": "ICS4ICS Workshop - OSP Cyber Academy",
    "source_path": "D:\\ZORO\\company_intel\\data\\ospcyberacademy.com\\product\\ics4ics-workshop\\index.html",
    "page_title": "ICS4ICS Workshop - OSP Cyber Academy",
    "meta_description": "Course Code: ICS4ICS Course Duration: 1 day Level 1: Awareness Next virtual course: enquire for availability Next classroom course: enquire for availability"
  },
  {
    "domain": "ospcyberacademy.com",
    "page": "product/industrial-control-system-security-practitioner/index.html",
    "section": "General",
    "text": "Industrial Control System Security Practitioner - OSP Cyber Academy",
    "source_path": "D:\\ZORO\\company_intel\\data\\ospcyberacademy.com\\product\\industrial-control-system-security-practitioner\\index.html",
    "page_title": "Industrial Control System Security Practitioner - OSP Cyber Academy",
    "meta_description": "Course Code: ICS505 Course Duration: 5 days Level 5: Mastery Next virtual course: enquire for availability Next classroom course: enquire for availability"
  },
  {
    "domain": "ospcyberacademy.com",
    "page": "product/isa-iec62443-series-of-standards-fundamentals-course/index.html",
    "section": "General",
    "text": "ISA/IEC62443 Series of Standards Fundamentals Course - OSP Cyber Academy",
    "source_path": "D:\\ZORO\\company_intel\\data\\ospcyberacademy.com\\product\\isa-iec62443-series-of-standards-fundamentals-course\\index.html",
    "page_title": "ISA/IEC62443 Series of Standards Fundamentals Course - OSP Cyber Academy",
    "meta_description": "Course Code: ICS202 Course Duration: 2 days Level 1: Awareness Next virtual course: enquire for availability Next classroom course: 30th October"
  },
  {
    "domain": "ospcyberacademy.com",
    "page": "product/mobile-device-security-course/index.html",
    "section": "General",
    "text": "Mobile Device Security Course - OSP Cyber Academy",
    "source_path": "D:\\ZORO\\company_intel\\data\\ospcyberacademy.com\\product\\mobile-device-security-course\\index.html",
    "page_title": "Mobile Device Security Course - OSP Cyber Academy",
    "meta_description": "£8 per user/seat This course can be taken as part of an information Security or Cyber Resilience training programme or as a standalone course to raise awareness amongst your staff for mobile device security. This is an annual subscription product, managed via your account. Please see our T&Cs for more details."
  },
  {
    "domain": "ospcyberacademy.com",
    "page": "product/mobile-device-security-lms-package/index.html",
    "section": "Contact Information",
    "text": "Phone numbers: 1-500501-1000, 1001-25002501-5000, 5001-1500015001",
    "source_path": "D:\\ZORO\\company_intel\\data\\ospcyberacademy.com\\product\\mobile-device-security-lms-package\\index.html",
    "page_title": "Mobile Device Security LMS Package - OSP Cyber Academy",
    "meta_description": "The pricing model is based on the size of the organisation. This is a one-year renewable licence product. Please see our T&Cs for more details.",
    "structured_data": {
      "emails": [],
      "phones": [
        "1-500501-1000",
        "1001-25002501-5000",
        "5001-1500015001"
      ],
      "social_links": {
        "facebook": "https://www.facebook.com/OSPCyberAcademy/",
        "linkedin": "https://www.linkedin.com/company/operationalsecurityprofessionalsgrouplimited/",
        "x": "https://twitter.com/OSPcyberacademy",
        "youtube": "https://www.youtube.com/channel/UCsWyl7VLp7tdw5X32aUOsLw"
      }
    }
  },
  {
    "domain": "ospcyberacademy.com",
    "page": "product/mobile-device-security-lms-package/index.html",
    "section": "General",
    "text": "Mobile Device Security LMS Package - OSP Cyber Academy",
    "source_path": "D:\\ZORO\\company_intel\\data\\ospcyberacademy.com\\product\\mobile-device-security-lms-package\\index.html",
    "page_title": "Mobile Device Security LMS Package - OSP Cyber Academy",
    "meta_description": "The pricing model is based on the size of the organisation. This is a one-year renewable licence product. Please see our T&Cs for more details."
  },
  {
    "domain": "ospcyberacademy.com",
    "page": "product/open-source-internet-investigation-foundation/index.html",
    "section": "General",
    "text": "Open Source Internet Investigation Foundation - OSP Cyber Academy",
    "source_path": "D:\\ZORO\\company_intel\\data\\ospcyberacademy.com\\product\\open-source-internet-investigation-foundation\\index.html",
    "page_title": "Open Source Internet Investigation Foundation - OSP Cyber Academy",
    "meta_description": "Course Code: ICS4ICS Course Duration: 1 day Level 1: Awareness Next virtual course: enquire for availability Next classroom course: enquire for availability"
  },
  {
    "domain": "ospcyberacademy.com",
    "page": "product/ot-cyber-security-awareness-course-lms-package/index.html",
    "section": "Contact Information",
    "text": "Phone numbers: 1-500501-1000, 1001-25002501-5000, 5001-1500015001",
    "source_path": "D:\\ZORO\\company_intel\\data\\ospcyberacademy.com\\product\\ot-cyber-security-awareness-course-lms-package\\index.html",
    "page_title": "OT Cyber Security Awareness LMS Package - OSP Cyber Academy",
    "meta_description": "The pricing model is based on the size of the organisation. This is a one-year renewable licence product. Please see our T&Cs for more details.",
    "structured_data": {
      "emails": [],
      "phones": [
        "1-500501-1000",
        "1001-25002501-5000",
        "5001-1500015001"
      ],
      "social_links": {
        "facebook": "https://www.facebook.com/OSPCyberAcademy/",
        "linkedin": "https://www.linkedin.com/company/operationalsecurityprofessionalsgrouplimited/",
        "x": "https://twitter.com/OSPcyberacademy",
        "youtube": "https://www.youtube.com/channel/UCsWyl7VLp7tdw5X32aUOsLw"
      }
    }
  },
  {
    "domain": "ospcyberacademy.com",
    "page": "product/ot-cyber-security-awareness-course-lms-package/index.html",
    "section": "General",
    "text": "OT Cyber Security Awareness LMS Package - OSP Cyber Academy",
    "source_path": "D:\\ZORO\\company_intel\\data\\ospcyberacademy.com\\product\\ot-cyber-security-awareness-course-lms-package\\index.html",
    "page_title": "OT Cyber Security Awareness LMS Package - OSP Cyber Academy",
    "meta_description": "The pricing model is based on the size of the organisation. This is a one-year renewable licence product. Please see our T&Cs for more details."
  },
  {
    "domain": "ospcyberacademy.com",
    "page": "product/ot-cyber-security-awareness-course.html",
    "section": "General",
    "text": "OT Cyber Security Awareness Course - OSP Cyber Academy",
    "source_path": "D:\\ZORO\\company_intel\\data\\ospcyberacademy.com\\product\\ot-cyber-security-awareness-course.html",
    "page_title": "OT Cyber Security Awareness Course - OSP Cyber Academy",
    "meta_description": "£40 per user/seat This is an annual subscription product, managed via your account. Please see our T&Cs for more details. Enquire for pricing on orders of 500+ courses."
  },
  {
    "domain": "ospcyberacademy.com",
    "page": "product/ot-cyber-security-awareness-course/index.html",
    "section": "General",
    "text": "OT Cyber Security Awareness Course - OSP Cyber Academy",
    "source_path": "D:\\ZORO\\company_intel\\data\\ospcyberacademy.com\\product\\ot-cyber-security-awareness-course\\index.html",
    "page_title": "OT Cyber Security Awareness Course - OSP Cyber Academy",
    "meta_description": "£40 per user/seat This is an annual subscription product, managed via your account. Please see our T&Cs for more details. Enquire for pricing on orders of 500+ courses."
  },
  {
    "domain": "ospcyberacademy.com",
    "page": "product/password-and-access-management-course/index.html",
    "section": "General",
    "text": "Password and Access Management Course - OSP Cyber Academy",
    "source_path": "D:\\ZORO\\company_intel\\data\\ospcyberacademy.com\\product\\password-and-access-management-course\\index.html",
    "page_title": "Password and Access Management Course - OSP Cyber Academy",
    "meta_description": "£8 per user/seat This is an annual subscription product, managed via your account. Please see our T&Cs for more details. Enquire for pricing on orders of 500+ courses."
  },
  {
    "domain": "ospcyberacademy.com",
    "page": "product/password-and-access-management-lms-package/index.html",
    "section": "Contact Information",
    "text": "Phone numbers: 1-500501-1000, 1001-25002501-5000, 5001-1500015001",
    "source_path": "D:\\ZORO\\company_intel\\data\\ospcyberacademy.com\\product\\password-and-access-management-lms-package\\index.html",
    "page_title": "Password and Access Management LMS Package - OSP Cyber Academy",
    "meta_description": "The pricing model is based on the size of the organisation. This is a one-year renewable licence product. Please see our T&Cs for more details.",
    "structured_data": {
      "emails": [],
      "phones": [
        "1-500501-1000",
        "1001-25002501-5000",
        "5001-1500015001"
      ],
      "social_links": {
        "facebook": "https://www.facebook.com/OSPCyberAcademy/",
        "linkedin": "https://www.linkedin.com/company/operationalsecurityprofessionalsgrouplimited/",
        "x": "https://twitter.com/OSPcyberacademy",
        "youtube": "https://www.youtube.com/channel/UCsWyl7VLp7tdw5X32aUOsLw"
      }
    }
  },
  {
    "domain": "ospcyberacademy.com",
    "page": "product/password-and-access-management-lms-package/index.html",
    "section": "General",
    "text": "Password and Access Management LMS Package - OSP Cyber Academy",
    "source_path": "D:\\ZORO\\company_intel\\data\\ospcyberacademy.com\\product\\password-and-access-management-lms-package\\index.html",
    "page_title": "Password and Access Management LMS Package - OSP Cyber Academy",
    "meta_description": "The pricing model is based on the size of the organisation. This is a one-year renewable licence product. Please see our T&Cs for more details."
  },
  {
    "domain": "ospcyberacademy.com",
    "page": "product/pathway-to-information-security-lms-package/index.html",
    "section": "Contact Information",
    "text": "Phone numbers: 1-500501-1000, 1001-25002501-5000, 5001-1500015001",
    "source_path": "D:\\ZORO\\company_intel\\data\\ospcyberacademy.com\\product\\pathway-to-information-security-lms-package\\index.html",
    "page_title": "Pathway To Information Security LMS Package - OSP Cyber Academy",
    "meta_description": "The pricing model is based on the size of the organisation. This is a one-year renewable licence product. Please see our T&Cs for more details.",
    "structured_data": {
      "emails": [],
      "phones": [
        "1-500501-1000",
        "1001-25002501-5000",
        "5001-1500015001"
      ],
      "social_links": {
        "facebook": "https://www.facebook.com/OSPCyberAcademy/",
        "linkedin": "https://www.linkedin.com/company/operationalsecurityprofessionalsgrouplimited/",
        "x": "https://twitter.com/OSPcyberacademy",
        "youtube": "https://www.youtube.com/channel/UCsWyl7VLp7tdw5X32aUOsLw"
      }
    }
  },
  {
    "domain": "ospcyberacademy.com",
    "page": "product/pathway-to-information-security-lms-package/index.html",
    "section": "General",
    "text": "Pathway To Information Security LMS Package - OSP Cyber Academy",
    "source_path": "D:\\ZORO\\company_intel\\data\\ospcyberacademy.com\\product\\pathway-to-information-security-lms-package\\index.html",
    "page_title": "Pathway To Information Security LMS Package - OSP Cyber Academy",
    "meta_description": "The pricing model is based on the size of the organisation. This is a one-year renewable licence product. Please see our T&Cs for more details."
  },
  {
    "domain": "ospcyberacademy.com",
    "page": "product/penetration-testing-essentials/index.html",
    "section": "General",
    "text": "Penetration Testing Essentials - OSP Cyber Academy",
    "source_path": "D:\\ZORO\\company_intel\\data\\ospcyberacademy.com\\product\\penetration-testing-essentials\\index.html",
    "page_title": "Penetration Testing Essentials - OSP Cyber Academy",
    "meta_description": "Course Code: ACT310 Course Duration: 4 days Level 3: Practitioner Next virtual course: enquire for availability Next classroom course: enquire for availability"
  },
  {
    "domain": "ospcyberacademy.com",
    "page": "product/phishing-and-social-engineering-course/index.html",
    "section": "General",
    "text": "Phishing and Social Engineering Course - OSP Cyber Academy",
    "source_path": "D:\\ZORO\\company_intel\\data\\ospcyberacademy.com\\product\\phishing-and-social-engineering-course\\index.html",
    "page_title": "Phishing and Social Engineering Course - OSP Cyber Academy",
    "meta_description": "£12 per user/seat This is an annual subscription product, managed via your account. Please see our T&Cs for more details. Enquire for pricing on orders of 500+ courses."
  },
  {
    "domain": "ospcyberacademy.com",
    "page": "product/phishing-and-social-engineering-lms-package/index.html",
    "section": "Contact Information",
    "text": "Phone numbers: 1-500501-1000, 1001-25002501-5000, 5001-1500015001",
    "source_path": "D:\\ZORO\\company_intel\\data\\ospcyberacademy.com\\product\\phishing-and-social-engineering-lms-package\\index.html",
    "page_title": "Phishing and Social Engineering LMS Package - OSP Cyber Academy",
    "meta_description": "The pricing model is based on the size of the organisation. This is a one-year renewable licence product. Please see our T&Cs for more details.",
    "structured_data": {
      "emails": [],
      "phones": [
        "1-500501-1000",
        "1001-25002501-5000",
        "5001-1500015001"
      ],
      "social_links": {
        "facebook": "https://www.facebook.com/OSPCyberAcademy/",
        "linkedin": "https://www.linkedin.com/company/operationalsecurityprofessionalsgrouplimited/",
        "x": "https://twitter.com/OSPcyberacademy",
        "youtube": "https://www.youtube.com/channel/UCsWyl7VLp7tdw5X32aUOsLw"
      }
    }
  },
  {
    "domain": "ospcyberacademy.com",
    "page": "product/phishing-and-social-engineering-lms-package/index.html",
    "section": "General",
    "text": "Phishing and Social Engineering LMS Package - OSP Cyber Academy",
    "source_path": "D:\\ZORO\\company_intel\\data\\ospcyberacademy.com\\product\\phishing-and-social-engineering-lms-package\\index.html",
    "page_title": "Phishing and Social Engineering LMS Package - OSP Cyber Academy",
    "meta_description": "The pricing model is based on the size of the organisation. This is a one-year renewable licence product. Please see our T&Cs for more details."
  },
  {
    "domain": "ospcyberacademy.com",
    "page": "product/ransomware-and-malware-course/index.html",
    "section": "General",
    "text": "Ransomware and Malware Course - OSP Cyber Academy",
    "source_path": "D:\\ZORO\\company_intel\\data\\ospcyberacademy.com\\product\\ransomware-and-malware-course\\index.html",
    "page_title": "Ransomware and Malware Course - OSP Cyber Academy",
    "meta_description": "£8 per user/seat This is an annual subscription product, managed via your account. Please see our T&Cs for more details. Enquire for pricing on orders of 500+ courses."
  },
  {
    "domain": "ospcyberacademy.com",
    "page": "product/ransomware-and-malware-lms-package/index.html",
    "section": "Contact Information",
    "text": "Phone numbers: 1-500501-1000, 1001-25002501-5000, 5001-1500015001",
    "source_path": "D:\\ZORO\\company_intel\\data\\ospcyberacademy.com\\product\\ransomware-and-malware-lms-package\\index.html",
    "page_title": "Ransomware and Malware LMS Package - OSP Cyber Academy",
    "meta_description": "The pricing model is based on the size of the organisation. This is a one-year renewable licence product. Please see our T&Cs for more details.",
    "structured_data": {
      "emails": [],
      "phones": [
        "1-500501-1000",
        "1001-25002501-5000",
        "5001-1500015001"
      ],
      "social_links": {
        "facebook": "https://www.facebook.com/OSPCyberAcademy/",
        "linkedin": "https://www.linkedin.com/company/operationalsecurityprofessionalsgrouplimited/",
        "x": "https://twitter.com/OSPcyberacademy",
        "youtube": "https://www.youtube.com/channel/UCsWyl7VLp7tdw5X32aUOsLw"
      }
    }
  },
  {
    "domain": "ospcyberacademy.com",
    "page": "product/ransomware-and-malware-lms-package/index.html",
    "section": "General",
    "text": "Ransomware and Malware LMS Package - OSP Cyber Academy",
    "source_path": "D:\\ZORO\\company_intel\\data\\ospcyberacademy.com\\product\\ransomware-and-malware-lms-package\\index.html",
    "page_title": "Ransomware and Malware LMS Package - OSP Cyber Academy",
    "meta_description": "The pricing model is based on the size of the organisation. This is a one-year renewable licence product. Please see our T&Cs for more details."
  },
  {
    "domain": "ospcyberacademy.com",
    "page": "product/securing-ics-becoming-an-industrial-cyber-security-professional/index.html",
    "section": "General",
    "text": "Securing ICS: Becoming an Industrial Cyber Security Professional - OSP Cyber Academy",
    "source_path": "D:\\ZORO\\company_intel\\data\\ospcyberacademy.com\\product\\securing-ics-becoming-an-industrial-cyber-security-professional\\index.html",
    "page_title": "Securing ICS: Becoming an Industrial Cyber Security Professional - OSP Cyber Academy",
    "meta_description": "Course Code: 405 Course Duration: 5 day Level 4: Senior Practitioner Next virtual course: enquire for availability Next classroom course: 2nd to 6th December"
  },
  {
    "domain": "ospcyberacademy.com",
    "page": "product/subject-access-request-course-lms-package/index.html",
    "section": "Contact Information",
    "text": "Phone numbers: 1-500501-1000, 1001-25002501-5000, 5001-1500015001",
    "source_path": "D:\\ZORO\\company_intel\\data\\ospcyberacademy.com\\product\\subject-access-request-course-lms-package\\index.html",
    "page_title": "Subject Access Request (SAR) LMS Package - OSP Cyber Academy",
    "meta_description": "The pricing model is based on the size of the organisation. This is a one-year renewable licence product. Please see our T&Cs for more details.",
    "structured_data": {
      "emails": [],
      "phones": [
        "1-500501-1000",
        "1001-25002501-5000",
        "5001-1500015001"
      ],
      "social_links": {
        "facebook": "https://www.facebook.com/OSPCyberAcademy/",
        "linkedin": "https://www.linkedin.com/company/operationalsecurityprofessionalsgrouplimited/",
        "x": "https://twitter.com/OSPcyberacademy",
        "youtube": "https://www.youtube.com/channel/UCsWyl7VLp7tdw5X32aUOsLw"
      }
    }
  },
  {
    "domain": "ospcyberacademy.com",
    "page": "product/subject-access-request-course-lms-package/index.html",
    "section": "General",
    "text": "Subject Access Request (SAR) LMS Package - OSP Cyber Academy",
    "source_path": "D:\\ZORO\\company_intel\\data\\ospcyberacademy.com\\product\\subject-access-request-course-lms-package\\index.html",
    "page_title": "Subject Access Request (SAR) LMS Package - OSP Cyber Academy",
    "meta_description": "The pricing model is based on the size of the organisation. This is a one-year renewable licence product. Please see our T&Cs for more details."
  },
  {
    "domain": "ospcyberacademy.com",
    "page": "product/subject-access-request-sar-course/index.html",
    "section": "General",
    "text": "Subject Access Request (SAR) Course - OSP Cyber Academy",
    "source_path": "D:\\ZORO\\company_intel\\data\\ospcyberacademy.com\\product\\subject-access-request-sar-course\\index.html",
    "page_title": "Subject Access Request (SAR) Course - OSP Cyber Academy",
    "meta_description": "£48 per user/seat This is an annual subscription product, managed via your account. Please see our T&Cs for more details."
  },
  {
    "domain": "ospcyberacademy.com",
    "page": "product/supply-chain-course/index.html",
    "section": "General",
    "text": "Supply Chain Course - OSP Cyber Academy",
    "source_path": "D:\\ZORO\\company_intel\\data\\ospcyberacademy.com\\product\\supply-chain-course\\index.html",
    "page_title": "Supply Chain Course - OSP Cyber Academy",
    "meta_description": "£24 per user/seat This is an annual subscription product, managed via your account. Please see our T&Cs for more details. This course can be taken as part of an information Security or Cyber Resilience training programme or as a standalone course to raise awareness around Supply Chain Security."
  },
  {
    "domain": "ospcyberacademy.com",
    "page": "services/index.html",
    "section": "General",
    "text": "Services - OSP Cyber Academy",
    "source_path": "D:\\ZORO\\company_intel\\data\\ospcyberacademy.com\\services\\index.html",
    "page_title": "Services - OSP Cyber Academy",
    "meta_description": "Data Protection andCyber Security Services OSP Group are the only […]"
  },
  {
    "domain": "ospcyberacademy.com",
    "page": "shop/index.html",
    "section": "General",
    "text": "Shop - OSP Cyber Academy",
    "source_path": "D:\\ZORO\\company_intel\\data\\ospcyberacademy.com\\shop\\index.html",
    "page_title": "Shop - OSP Cyber Academy",
    "meta_description": ""
  },
  {
    "domain": "ospcyberacademy.com",
    "page": "siker-ot-courses/index.html",
    "section": "General",
    "text": "SIKER OT Courses - OSP Cyber Academy",
    "source_path": "D:\\ZORO\\company_intel\\data\\ospcyberacademy.com\\siker-ot-courses\\index.html",
    "page_title": "SIKER OT Courses - OSP Cyber Academy",
    "meta_description": "SIKER OT Courses Siker courses are developed by experienced OT […]"
  },
  {
    "domain": "ospcyberacademy.com",
    "page": "terms-conditions-business.html",
    "section": "General",
    "text": "Terms & Conditions – Business - OSP Cyber Academy",
    "source_path": "D:\\ZORO\\company_intel\\data\\ospcyberacademy.com\\terms-conditions-business.html",
    "page_title": "Terms & Conditions – Business - OSP Cyber Academy",
    "meta_description": "STANDARD TERMS OF BUSINESS 3.1 We shall provide the Services […]"
  },
  {
    "domain": "ospcyberacademy.com",
    "page": "terms-conditions-business/index.html",
    "section": "General",
    "text": "Terms & Conditions – Business - OSP Cyber Academy",
    "source_path": "D:\\ZORO\\company_intel\\data\\ospcyberacademy.com\\terms-conditions-business\\index.html",
    "page_title": "Terms & Conditions – Business - OSP Cyber Academy",
    "meta_description": "STANDARD TERMS OF BUSINESS 3.1 We shall provide the Services […]"
  },
  {
    "domain": "ospcyberacademy.com",
    "page": "terms-conditions-consumer/index.html",
    "section": "General",
    "text": "Terms & Conditions – Consumer - OSP Cyber Academy",
    "source_path": "D:\\ZORO\\company_intel\\data\\ospcyberacademy.com\\terms-conditions-consumer\\index.html",
    "page_title": "Terms & Conditions – Consumer - OSP Cyber Academy",
    "meta_description": "Terms and Conditions of Supply of Goods or Services by […]"
  },
  {
    "domain": "ospcyberacademy.com",
    "page": "terms-conditions-events/index.html",
    "section": "General",
    "text": "Terms & Conditions – Events - OSP Cyber Academy",
    "source_path": "D:\\ZORO\\company_intel\\data\\ospcyberacademy.com\\terms-conditions-events\\index.html",
    "page_title": "Terms & Conditions – Events - OSP Cyber Academy",
    "meta_description": "Terms and Conditions of Events by Operational Security Professionals Group […]"
  },
  {
    "domain": "ospcyberacademy.com",
    "page": "terms-conditions/index.html",
    "section": "General",
    "text": "Terms of Website Use - OSP Cyber Academy",
    "source_path": "D:\\ZORO\\company_intel\\data\\ospcyberacademy.com\\terms-conditions\\index.html",
    "page_title": "Terms of Website Use - OSP Cyber Academy",
    "meta_description": "This page (and the documents it refers to) tells you […]"
  },
  {
    "domain": "ospcyberacademy.com",
    "page": "the-digital-operational-resilience-act-dora-ensuring-stability-in-financial-services/index.html",
    "section": "General",
    "text": "The Digital Operational Resilience Act (DORA): Ensuring Stability in Financial Services - OSP Cyber Academy",
    "source_path": "D:\\ZORO\\company_intel\\data\\ospcyberacademy.com\\the-digital-operational-resilience-act-dora-ensuring-stability-in-financial-services\\index.html",
    "page_title": "The Digital Operational Resilience Act (DORA): Ensuring Stability in Financial Services - OSP Cyber Academy",
    "meta_description": "As with any regulatory change, the key to success lies in thorough preparation, robust execution, and a commitment to continuous improvement."
  },
  {
    "domain": "ospcyberacademy.com",
    "page": "training.html",
    "section": "General",
    "text": "Training - OSP Cyber Academy",
    "source_path": "D:\\ZORO\\company_intel\\data\\ospcyberacademy.com\\training.html",
    "page_title": "Training - OSP Cyber Academy",
    "meta_description": "Training Courses Our courses are developed by experienced Data Protection […]"
  },
  {
    "domain": "ospcyberacademy.com",
    "page": "training/index.html",
    "section": "General",
    "text": "Training - OSP Cyber Academy",
    "source_path": "D:\\ZORO\\company_intel\\data\\ospcyberacademy.com\\training\\index.html",
    "page_title": "Training - OSP Cyber Academy",
    "meta_description": "Training Courses Our courses are developed by experienced Data Protection […]"
  }
]