[
  {
    "domain": "12d.co.uk",
    "page": "index.html",
    "section": "Contact Information",
    "text": "Phone numbers: 02-132\n1, 19650, 2025 12, +44 20 4592 0657\n\nFooter information: Discover 12d todayBook your personalised demo today and find out why leading built environment companies choose 12d to help deliver their projects.Book a demoWeWork Moor PlacePrivate Office 02-1321 Fore Street AvenueLondon, EC2Y 9DTUnited KingdomT: +44 20 4592 0657© 2025 12d UK LtdWebsite by FGMWho we serveSurveyorsDesignersWater EngineersBIM & Digital Engineering ManagersBook a demoSupportPrivacy NoticeCookie NoticeSecurity StatementContact UsLinkedInInstagramFacebookYouTube",
    "source_path": "D:\\ZORO\\company_intel\\data\\12d.co.uk\\index.html",
    "page_title": "12d | Construction & Engineering Software for Infrastructure",
    "meta_description": "Construction and engineering software for civil infrastructure projects. Design, survey and manage drawings, models and data in one environment with 12d.",
    "structured_data": {
      "emails": [],
      "phones": [
        "02-132\n1",
        "19650",
        "2025 12",
        "+44 20 4592 0657"
      ],
      "social_links": {}
    }
  }
]